vulnmap/__init__.py
vulnmap/vulnmap.py
vulnmap/ai_providers/__init__.py
vulnmap/ai_providers/claude_provider.py
vulnmap/ai_providers/gemini.py
vulnmap/ai_providers/grok_provider.py
vulnmap/ai_providers/ollama_provider.py
vulnmap/ai_providers/openai_provider.py
vulnmap/ai_providers/provider_manager.py
vulnmap/core/__init__.py
vulnmap/core/ai_payload_generator.py
vulnmap/core/plugin_manager.py
vulnmap/core/report_generator.py
vulnmap/core/scanner_engine.py
vulnmap/core/vulnerability_scanner.py
vulnmap/modules/__init__.py
vulnmap/modules/api_security/__init__.py
vulnmap/modules/api_security/api_tester.py
vulnmap/modules/api_security/graphql_tester.py
vulnmap/modules/authentication/__init__.py
vulnmap/modules/authentication/auth_tester.py
vulnmap/modules/business_logic/__init__.py
vulnmap/modules/business_logic/logic_tester.py
vulnmap/modules/collaboration/__init__.py
vulnmap/modules/collaboration/collaborative_scanner.py
vulnmap/modules/file_upload/__init__.py
vulnmap/modules/file_upload/upload_tester.py
vulnmap/modules/ml_detection/__init__.py
vulnmap/modules/ml_detection/anomaly_detector.py
vulnmap/modules/payload_obfuscation/__init__.py
vulnmap/modules/payload_obfuscation/obfuscator.py
vulnmap/modules/reconnaissance/__init__.py
vulnmap/modules/reconnaissance/osint_enhanced.py
vulnmap/modules/reconnaissance/recon_engine.py
vulnmap/modules/reporting/__init__.py
vulnmap/modules/reporting/interactive_report.py
vulnmap/modules/websocket/__init__.py
vulnmap/modules/websocket/websocket_tester.py
vulnmap/utils/__init__.py
vulnmap/utils/config_loader.py
vulnmap/utils/http_client.py
vulnmap/utils/logger.py
vulnmap/utils/notification_manager.py
vulnmap/utils/parser.py
vulnmap-1.3.3.dist-info/licenses/LICENSE
vulnmap-1.3.3.dist-info/METADATA
vulnmap-1.3.3.dist-info/WHEEL
vulnmap-1.3.3.dist-info/entry_points.txt
vulnmap-1.3.3.dist-info/top_level.txt
vulnmap-1.3.3.dist-info/RECORD
