Metadata-Version: 2.4
Name: vulnmap
Version: 1.3.3
Summary: Advanced AI-Driven Penetration Testing Tool
Home-page: https://github.com/AL-MARID/Vulnmap
Author: AL-MARID
Author-email: security@almarid.io
Project-URL: Bug Reports, https://github.com/AL-MARID/Vulnmap/issues
Project-URL: Source, https://github.com/AL-MARID/Vulnmap
Project-URL: Documentation, https://github.com/AL-MARID/Vulnmap/wiki
Keywords: security penetration-testing vulnerability-scanner ai pentesting
Classifier: Development Status :: 4 - Beta
Classifier: Intended Audience :: Information Technology
Classifier: Intended Audience :: Developers
Classifier: Topic :: Security
Classifier: License :: OSI Approved :: MIT License
Classifier: Programming Language :: Python :: 3
Classifier: Programming Language :: Python :: 3.8
Classifier: Programming Language :: Python :: 3.9
Classifier: Programming Language :: Python :: 3.10
Classifier: Programming Language :: Python :: 3.11
Classifier: Programming Language :: Python :: 3.12
Classifier: Operating System :: OS Independent
Requires-Python: >=3.8
License-File: LICENSE
Dynamic: author
Dynamic: author-email
Dynamic: classifier
Dynamic: description
Dynamic: description-content-type
Dynamic: home-page
Dynamic: keywords
Dynamic: license-file
Dynamic: project-url
Dynamic: requires-python
Dynamic: summary
